Metadata-Version: 2.4
Name: llama-index-storage-index-store-gel
Version: 0.2.1
Summary: llama-index index_store gel integration
Author-email: Your Name <you@example.com>
License-Expression: MIT
License-File: LICENSE
Requires-Python: <4.0,>=3.9
Requires-Dist: llama-index-core<0.15,>=0.13.0
Requires-Dist: llama-index-storage-kvstore-gel<0.3,>=0.2.0
